envfiles/__init__.py
envfiles/envfiles.py
envfiles-0.1.1.dist-info/LICENSE
envfiles-0.1.1.dist-info/WHEEL
envfiles-0.1.1.dist-info/METADATA
envfiles-0.1.1.dist-info/RECORD
