Metadata-Version: 2.1
Name: envfiles
Version: 0.1.1
Summary: Simple layered loading of env files
Keywords: environment,variables,12-factor
Author-email: Yeray Díaz <yeraydiazdiaz@gmail.com>
Requires-Python: >=3.6, <4
Classifier: Development Status :: 5 - Production/Stable
Classifier: Intended Audience :: Developers
Classifier: Natural Language :: English
Classifier: Operating System :: OS Independent
Classifier: Programming Language :: Python
Classifier: Programming Language :: Python :: 3
Classifier: Programming Language :: Python :: 3.6
Classifier: Programming Language :: Python :: 3.7
Classifier: Programming Language :: Python :: 3.8
Classifier: Programming Language :: Python :: 3.9
Classifier: Programming Language :: Python :: 3.10
Classifier: Programming Language :: Python :: Implementation :: CPython
Classifier: Topic :: Software Development :: Libraries :: Python Modules
Classifier: License :: OSI Approved :: MIT License
Requires-Dist: black ; extra == "dev"
Requires-Dist: flake8 ; extra == "dev"
Requires-Dist: flake8-bugbear ; extra == "dev"
Requires-Dist: flake8-comprehensions ; extra == "dev"
Requires-Dist: flake8-pie ; extra == "dev"
Requires-Dist: ipython ; extra == "dev"
Requires-Dist: mypy ; extra == "dev"
Requires-Dist: pdbpp ; extra == "dev"
Requires-Dist: wheel ; extra == "dev"
Requires-Dist: isort ; extra == "dev"
Requires-Dist: devtools[pygments] ; extra == "dev"
Requires-Dist: nox ; extra == "dev"
Requires-Dist: pytest ; extra == "test"
Requires-Dist: pytest-mock ; extra == "test"
Requires-Dist: pytest-cov ; extra == "test"
Project-URL: Changelog, https://github.com/yeraydiazdiaz/envfiles/blob/master/CHANGELOG.md
Project-URL: Code, https://github.com/yeraydiazdiaz/envfiles
Project-URL: Issue tracker, https://github.com/yeraydiazdiaz/envfiles/issues
Provides-Extra: dev
Provides-Extra: test
